networksage_wrappers/wrappers/__init__.py
networksage_wrappers/wrappers/tests.py
networksage_wrappers/wrappers/wrappers.py
networksage_wrappers/wrappers/tests/pcap_test.pcap
networksage_wrappers/wrappers/tests/secflow_test.sf
networksage_wrappers/wrappers/tests/test_conn.log
networksage_wrappers/wrappers/tests/test_dns.log
networksage_wrappers-0.9.8.dist-info/LICENSE
networksage_wrappers-0.9.8.dist-info/METADATA
networksage_wrappers-0.9.8.dist-info/WHEEL
networksage_wrappers-0.9.8.dist-info/top_level.txt
networksage_wrappers-0.9.8.dist-info/RECORD
