Metadata-Version: 2.1
Name: networksage-wrappers
Version: 0.9.8
Summary: Wrappers to make leveraging NetworkSage's APIs simple.
Home-page: https://gitlab.com/networksage-public-tools/networksage-wrappers
Author: David Pearson
Author-email: david@seclarity.io
License: UNKNOWN
Project-URL: Bug Tracker, https://gitlab.com/networksage-public-tools/networksage-wrappers/issues
Platform: UNKNOWN
Classifier: Programming Language :: Python :: 3
Classifier: License :: OSI Approved :: Apache Software License
Classifier: Operating System :: MacOS :: MacOS X
Classifier: Operating System :: Microsoft :: Windows
Classifier: Operating System :: POSIX :: Linux
Requires-Python: >=3.8.10
License-File: LICENSE
Requires-Dist: ipaddress (>=1.0.23)
Requires-Dist: pathlib (>=1.0.1)
Requires-Dist: python-dateutil (>=2.8.2)
Requires-Dist: jsonify (>=0.5)
Requires-Dist: requests (>=2.27.1)
